jarvisAPILibrary
