Metadata-Version: 2.2
Name: jarvis_api_library
Version: 1.3.3
Summary: A library for interacting with API's to be used within The J.A.R.V.I.S. Project.
Author: Samuel Lewis
Requires-Dist: requests>=2.32.3
Dynamic: author
Dynamic: description
Dynamic: description-content-type
Dynamic: requires-dist
Dynamic: summary
